pytweetql/__init__.py
pytweetql/_logging.py
pytweetql/_typing.py
pytweetql/_utils/__init__.py
pytweetql/_utils/_data_structures.py
pytweetql/_utils/_utils.py
pytweetql/constants.py
pytweetql/errors.py
pytweetql/parsing.py
pytweetql/response/__init__.py
pytweetql/response/_base_response.py
pytweetql/response/api_error.py
pytweetql/response/tweet.py
pytweetql/response/twitterlist.py
pytweetql/response/user.py
pytweetql/validation/__init__.py
pytweetql/validation/_base_validation.py
pytweetql/validation/_node_path.py
pytweetql/validation/_nodes.py
pytweetql/validation/validation.py
pytweetql-1.0.0.dist-info/LICENSE
pytweetql-1.0.0.dist-info/METADATA
pytweetql-1.0.0.dist-info/WHEEL
pytweetql-1.0.0.dist-info/RECORD
