Metadata-Version: 2.1
Name: pytweetql
Version: 1.0.0
Summary: Easy parsing of Twitter GraphQL API responses
License: MIT
Author: galactixx
Requires-Python: >=3.12,<4.0
Classifier: License :: OSI Approved :: MIT License
Classifier: Programming Language :: Python :: 3
Classifier: Programming Language :: Python :: 3.12
Requires-Dist: python-dateutil (>=2.8.2,<3.0.0)
